{"1166":{"registrationStatus":"DOMESTIK-TERDAFTAR","systemName":"PORTAL PENDAFTARAN SEKOLAH PASAR MODAL (SPM)","systemUrl":"sekolahpasarmodal.idx.co.id","operatorSector":"Sektor Keuangan, Sektor Keuangan","operatorName":"BURSA EFEK INDONESIA","registrationDate":"2021-06-02","registrationID":"https://pse.komdigi.go.id/tdpse-detail/1166","raw":{"id":"9cb1ab6b-a49a-4802-a2d9-0aa8dbc74fa8","nama_pse":"BURSA EFEK INDONESIA","nama_se":"PORTAL PENDAFTARAN SEKOLAH PASAR MODAL (SPM)","sektor":"Sektor Keuangan, Sektor Keuangan","tanggal_terbit":"2021-06-02","url_tdpse_detail":"https://pse.komdigi.go.id/tdpse-detail/1166","website":"sekolahpasarmodal.idx.co.id"}}}