{"12181":{"registrationStatus":"DOMESTIK-TERDAFTAR","systemName":"WEBSITE PORTFOLIO","systemUrl":"bprspnmmentari.co.id","operatorSector":"Sektor Keuangan","operatorName":"BANK PEREKONOMIAN RAKYAT SYARIAH PNM MENTARI","registrationDate":"2022-11-09","registrationID":"https://pse.komdigi.go.id/tdpse-detail/12181","raw":{"id":"9cb1ac06-597c-4678-ab2e-1071a7770e1f","nama_pse":"BANK PEREKONOMIAN RAKYAT SYARIAH PNM MENTARI","nama_se":"WEBSITE PORTFOLIO","sektor":"Sektor Keuangan","tanggal_terbit":"2022-11-09","url_tdpse_detail":"https://pse.komdigi.go.id/tdpse-detail/12181","website":"bprspnmmentari.co.id"}}}