{"11992":{"registrationStatus":"DOMESTIK-TERDAFTAR","systemName":"PT DIGIVO KREATIF INDONESIA","systemUrl":"digivo.co.id","operatorSector":"Sektor Teknologi Informasi dan Komunikasi","operatorName":"DIGIVO KREATIF INDONESIA","registrationDate":"2022-10-27","registrationID":"https://pse.komdigi.go.id/tdpse-detail/11992","raw":{"id":"9cb1ac05-2fc8-489c-a6b7-16c22b2e72e9","nama_pse":"DIGIVO KREATIF INDONESIA","nama_se":"PT DIGIVO KREATIF INDONESIA","sektor":"Sektor Teknologi Informasi dan Komunikasi","tanggal_terbit":"2022-10-27","url_tdpse_detail":"https://pse.komdigi.go.id/tdpse-detail/11992","website":"digivo.co.id"}}}