{"17430":{"registrationStatus":"DOMESTIK-TERDAFTAR","systemName":"FIZZ PEDIA","systemUrl":"fizzpedia.co.id","operatorSector":"Sektor Perdagangan","operatorName":"HAFIZ QADRIL","registrationDate":"2024-01-20","registrationID":"https://pse.komdigi.go.id/tdpse-detail/17430","raw":{"id":"9cb1ac7b-b444-4eeb-bf10-dd50053a392a","nama_pse":"HAFIZ QADRIL","nama_se":"FIZZ PEDIA","sektor":"Sektor Perdagangan","tanggal_terbit":"2024-01-20","url_tdpse_detail":"https://pse.komdigi.go.id/tdpse-detail/17430","website":"fizzpedia.co.id"}}}