{"4296":{"registrationStatus":"DOMESTIK-TERDAFTAR","systemName":"GRAVEL","systemUrl":"gravel.co.id","operatorSector":"Sektor Perdagangan, Sektor Teknologi Informasi dan Komunikasi","operatorName":"GRAVEL TEKNOLOGI INDONESIA","registrationDate":"2022-06-08","registrationID":"https://pse.komdigi.go.id/tdpse-detail/4296","raw":{"id":"9cb1abac-c021-46eb-8163-0e03ad668bbe","nama_pse":"GRAVEL TEKNOLOGI INDONESIA","nama_se":"GRAVEL","sektor":"Sektor Perdagangan, Sektor Teknologi Informasi dan Komunikasi","tanggal_terbit":"2022-06-08","url_tdpse_detail":"https://pse.komdigi.go.id/tdpse-detail/4296","website":"gravel.co.id"}},"4749":{"registrationStatus":"DOMESTIK-TERDAFTAR","systemName":"GRAVEL DULUR","systemUrl":"gravel.co.id","operatorSector":"Sektor Perdagangan, Sektor Teknologi Informasi dan Komunikasi","operatorName":"GRAVEL TEKNOLOGI INDONESIA","registrationDate":"2022-06-24","registrationID":"https://pse.komdigi.go.id/tdpse-detail/4749","raw":{"id":"9cb1abad-f66a-4051-a4e8-318e59f1197b","nama_pse":"GRAVEL TEKNOLOGI INDONESIA","nama_se":"GRAVEL DULUR","sektor":"Sektor Perdagangan, Sektor Teknologi Informasi dan Komunikasi","tanggal_terbit":"2022-06-24","url_tdpse_detail":"https://pse.komdigi.go.id/tdpse-detail/4749","website":"gravel.co.id"}}}