{"18558":{"registrationStatus":"DOMESTIK-TERDAFTAR","systemName":"CLIENT JAVA GLOBAL FUTURES","systemUrl":"javafx.co.id","operatorSector":"Sektor Perdagangan","operatorName":"JAVA GLOBAL FUTURES","registrationDate":"2024-04-05","registrationID":"https://pse.komdigi.go.id/tdpse-detail/18558","raw":{"id":"9cb1ac82-9ea4-4b4a-8d57-ab7ad8896c3d","nama_pse":"JAVA GLOBAL FUTURES","nama_se":"CLIENT JAVA GLOBAL FUTURES","sektor":"Sektor Perdagangan","tanggal_terbit":"2024-04-05","url_tdpse_detail":"https://pse.komdigi.go.id/tdpse-detail/18558","website":"javafx.co.id"}}}