{"9321":{"registrationStatus":"DOMESTIK-TERDAFTAR","systemName":"PRODIA CHATBOT (TANIA)","systemUrl":"prodia.co.id","operatorSector":"Sektor Kesehatan","operatorName":"PRODIA WIDYAHUSADA","registrationDate":"2022-07-28","registrationID":"https://pse.komdigi.go.id/tdpse-detail/9321","raw":{"id":"9cb1abf6-0347-4c2a-9dd5-18e7b67c0134","nama_pse":"PRODIA WIDYAHUSADA","nama_se":"PRODIA CHATBOT (TANIA)","sektor":"Sektor Kesehatan","tanggal_terbit":"2022-07-28","url_tdpse_detail":"https://pse.komdigi.go.id/tdpse-detail/9321","website":"prodia.co.id"}}}