{"276":{"registrationStatus":"DOMESTIK-TERDAFTAR","systemName":"PROLINE FINANCE","systemUrl":"prolinefinance.co.id","operatorSector":"Sektor Keuangan, Sektor Keuangan","operatorName":"PROLINE FINANCE INDONESIA","registrationDate":"2021-03-04","registrationID":"https://pse.komdigi.go.id/tdpse-detail/276","raw":{"id":"9cb1ab7d-74ac-4cbb-9cb1-bb4a5c0f9027","nama_pse":"PROLINE FINANCE INDONESIA","nama_se":"PROLINE FINANCE","sektor":"Sektor Keuangan, Sektor Keuangan","tanggal_terbit":"2021-03-04","url_tdpse_detail":"https://pse.komdigi.go.id/tdpse-detail/276","website":"prolinefinance.co.id"}}}