{"21445":{"registrationStatus":"DOMESTIK-TERDAFTAR","systemName":"VIAPULSA GLOBAL INDONESIA","systemUrl":"viapulsa.co.id","operatorSector":"Sektor Perdagangan","operatorName":"VIAPULSA GLOBAL INDONESIA","registrationDate":"2024-12-04","registrationID":"https://pse.komdigi.go.id/tdpse-detail/21445","raw":{"id":"9da43de3-7c18-4895-996a-70ff2e180e6a","nama_pse":"VIAPULSA GLOBAL INDONESIA","nama_se":"VIAPULSA GLOBAL INDONESIA","sektor":"Sektor Perdagangan","tanggal_terbit":"2024-12-04","url_tdpse_detail":"https://pse.komdigi.go.id/tdpse-detail/21445","website":"viapulsa.co.id"}}}