{"14741":{"registrationStatus":"DOMESTIK-TERDAFTAR","systemName":"SISTEM INFORMASI RUMAH SAKIT PERTAMEDIKA (SIRUP)","systemUrl":"rspt.ihc.id","operatorSector":"Sektor Kesehatan","operatorName":"PERTAMINA BINA MEDIKA IHC","registrationDate":"2023-05-17","registrationID":"https://pse.komdigi.go.id/tdpse-detail/14741","raw":{"id":"9cb1ac43-e729-4384-b6c6-c7c28edaffcd","nama_pse":"PERTAMINA BINA MEDIKA IHC","nama_se":"SISTEM INFORMASI RUMAH SAKIT PERTAMEDIKA (SIRUP)","sektor":"Sektor Kesehatan","tanggal_terbit":"2023-05-17","url_tdpse_detail":"https://pse.komdigi.go.id/tdpse-detail/14741","website":"rspt.ihc.id"}}}