{"7202":{"registrationStatus":"DOMESTIK-DIHENTIKAN-SEMENTARA","systemName":"HOST KIOSINDONESIA","systemUrl":"host.kiosindonesia.com","operatorSector":"Sektor Perdagangan, Sektor Teknologi Informasi dan Komunikasi","operatorName":"KIOS TEKNOLOGI INDONESIA","registrationDate":"2022-07-19","registrationID":"https://pse.komdigi.go.id/tdpse-detail/7202","raw":{"id":"9cb1abb7-488a-4d54-8653-a8132470d2b1","nama_pse":"KIOS TEKNOLOGI INDONESIA","nama_se":"HOST KIOSINDONESIA","sektor":"Sektor Perdagangan, Sektor Teknologi Informasi dan Komunikasi","tanggal_terbit":"2022-07-19","url_tdpse_detail":"https://pse.komdigi.go.id/tdpse-detail/7202","website":"host.kiosindonesia.com"}}}