{"5016":{"registrationStatus":"DOMESTIK-TERDAFTAR","systemName":"ESBN","systemUrl":"esbn.panin.co.id","operatorSector":"Sektor Keuangan","operatorName":"BANK PAN INDONESIA","registrationDate":"2022-07-01","registrationID":"https://pse.komdigi.go.id/tdpse-detail/5016","raw":{"id":"9cb1abae-80e0-4e5d-9c5a-75d32b7193aa","nama_pse":"BANK PAN INDONESIA","nama_se":"ESBN","sektor":"Sektor Keuangan","tanggal_terbit":"2022-07-01","url_tdpse_detail":"https://pse.komdigi.go.id/tdpse-detail/5016","website":"esbn.panin.co.id"}}}