{"7660":{"registrationStatus":"DOMESTIK-TERDAFTAR","systemName":"APLIKASI BELANJA MADRASAH","systemUrl":"absah.id","operatorSector":"Sektor Perdagangan, Sektor Teknologi Informasi dan Komunikasi","operatorName":"GRATIS ONGKIR","registrationDate":"2022-07-20","registrationID":"https://pse.komdigi.go.id/tdpse-detail/7660","raw":{"id":"9cb1abc4-d08a-4f7b-b3f3-1d66a9205755","nama_pse":"GRATIS ONGKIR","nama_se":"APLIKASI BELANJA MADRASAH","sektor":"Sektor Perdagangan, Sektor Teknologi Informasi dan Komunikasi","tanggal_terbit":"2022-07-20","url_tdpse_detail":"https://pse.komdigi.go.id/tdpse-detail/7660","website":"absah.id"}}}