{"20505":{"registrationStatus":"DOMESTIK-TERDAFTAR","systemName":"ARMY NUTRITION INDONESIA","systemUrl":"armynutrition.id","operatorSector":"Sektor Perdagangan","operatorName":"ARMY NUTRITION INDONESIA","registrationDate":"2024-09-27","registrationID":"https://pse.komdigi.go.id/tdpse-detail/20505","raw":{"id":"9d1b6706-f6aa-41aa-82c7-71947bfce9b0","nama_pse":"ARMY NUTRITION INDONESIA","nama_se":"ARMY NUTRITION INDONESIA","sektor":"Sektor Perdagangan","tanggal_terbit":"2024-09-27","url_tdpse_detail":"https://pse.komdigi.go.id/tdpse-detail/20505","website":"armynutrition.id"}}}