{"13429":{"registrationStatus":"DOMESTIK-TERDAFTAR","systemName":"HIBURANKITA.ID","systemUrl":"hiburankita.id","operatorSector":"Sektor Teknologi Informasi dan Komunikasi","operatorName":"NOVAL KUSUMA","registrationDate":"2023-01-05","registrationID":"https://pse.komdigi.go.id/tdpse-detail/13429","raw":{"id":"9cb1ac18-9da2-47da-a544-1666bdb53137","nama_pse":"NOVAL KUSUMA","nama_se":"HIBURANKITA.ID","sektor":"Sektor Teknologi Informasi dan Komunikasi","tanggal_terbit":"2023-01-05","url_tdpse_detail":"https://pse.komdigi.go.id/tdpse-detail/13429","website":"hiburankita.id"}}}