{"18325":{"registrationStatus":"DOMESTIK-TERDAFTAR","systemName":"METROPOLIS.ID","systemUrl":"metropolis.id","operatorSector":"Sektor Teknologi Informasi dan Komunikasi","operatorName":"METRO INTER MEDIA","registrationDate":"2024-03-19","registrationID":"https://pse.komdigi.go.id/tdpse-detail/18325","raw":{"id":"9cb1ac6c-e0f8-4be2-a41c-f7c997cfdd85","nama_pse":"METRO INTER MEDIA","nama_se":"METROPOLIS.ID","sektor":"Sektor Teknologi Informasi dan Komunikasi","tanggal_terbit":"2024-03-19","url_tdpse_detail":"https://pse.komdigi.go.id/tdpse-detail/18325","website":"metropolis.id"}}}