{"22721":{"registrationStatus":"DOMESTIK-TERDAFTAR","systemName":"ZENDO APA AJA DIMANA AJA","systemUrl":"zendo.id","operatorSector":"Sektor Perdagangan, Sektor Transportasi","operatorName":"ZENDO JAYA GROUP","registrationDate":"2025-03-12","registrationID":"https://pse.komdigi.go.id/tdpse-detail/22721","raw":{"id":"9e6a2b8d-d08b-4ddd-b841-1f0229d42058","nama_pse":"ZENDO JAYA GROUP","nama_se":"ZENDO APA AJA DIMANA AJA","sektor":"Sektor Perdagangan, Sektor Transportasi","tanggal_terbit":"2025-03-12","url_tdpse_detail":"https://pse.komdigi.go.id/tdpse-detail/22721","website":"zendo.id"}}}