{"18479":{"registrationStatus":"DOMESTIK-TERDAFTAR","systemName":"ANJANA JAYA TEKNOLOGI","systemUrl":"anjanajayateknologi.com","operatorSector":"Sektor Perdagangan, Sektor Teknologi Informasi dan Komunikasi","operatorName":"ANJANA JAYA TEKNOLOGI","registrationDate":"2024-03-29","registrationID":"https://pse.komdigi.go.id/tdpse-detail/18479","raw":{"id":"9cb1ac6d-8e07-486d-8d1c-f1a5d3c39b69","nama_pse":"ANJANA JAYA TEKNOLOGI","nama_se":"ANJANA JAYA TEKNOLOGI","sektor":"Sektor Perdagangan, Sektor Teknologi Informasi dan Komunikasi","tanggal_terbit":"2024-03-29","url_tdpse_detail":"https://pse.komdigi.go.id/tdpse-detail/18479","website":"anjanajayateknologi.com"}}}