{"19460":{"registrationStatus":"DOMESTIK-TERDAFTAR","systemName":"MARTAMEDIKA","systemUrl":"dashboardmm.com","operatorSector":"Sektor Kesehatan, Sektor Teknologi Informasi dan Komunikasi","operatorName":"AIKO OLIVIA","registrationDate":"2024-07-10","registrationID":"https://pse.komdigi.go.id/tdpse-detail/19460","raw":{"id":"9cb1ac73-207f-499d-9fbb-1a186f957246","nama_pse":"AIKO OLIVIA","nama_se":"MARTAMEDIKA","sektor":"Sektor Kesehatan, Sektor Teknologi Informasi dan Komunikasi","tanggal_terbit":"2024-07-10","url_tdpse_detail":"https://pse.komdigi.go.id/tdpse-detail/19460","website":"dashboardmm.com"}}}