{"9816":{"registrationStatus":"DOMESTIK-TERDAFTAR","systemName":"DOCXPEDIA.COM","systemUrl":"docxpedia.com","operatorSector":"Sektor Teknologi Informasi dan Komunikasi","operatorName":"WAHLAN","registrationDate":"2022-08-03","registrationID":"https://pse.komdigi.go.id/tdpse-detail/9816","raw":{"id":"9cb1ac08-f68d-4daa-a635-5c6c9b24a52b","nama_pse":"WAHLAN","nama_se":"DOCXPEDIA.COM","sektor":"Sektor Teknologi Informasi dan Komunikasi","tanggal_terbit":"2022-08-03","url_tdpse_detail":"https://pse.komdigi.go.id/tdpse-detail/9816","website":"docxpedia.com"}}}