{"19464":{"registrationStatus":"DOMESTIK-TERDAFTAR","systemName":"GAJIHUB","systemUrl":"gajihub.com","operatorSector":"Sektor Teknologi Informasi dan Komunikasi","operatorName":"GAJIHUB BERHATI NYAMAN","registrationDate":"2024-07-11","registrationID":"https://pse.komdigi.go.id/tdpse-detail/19464","raw":{"id":"9cb1ac5d-fa95-4a0a-8942-914def699183","nama_pse":"GAJIHUB BERHATI NYAMAN","nama_se":"GAJIHUB","sektor":"Sektor Teknologi Informasi dan Komunikasi","tanggal_terbit":"2024-07-11","url_tdpse_detail":"https://pse.komdigi.go.id/tdpse-detail/19464","website":"gajihub.com"}}}