{"11883":{"registrationStatus":"DOMESTIK-TERDAFTAR","systemName":"GOKOMODO","systemUrl":"gokomodo.com","operatorSector":"Sektor Teknologi Informasi dan Komunikasi","operatorName":"SAKA UNITI INDONESIA","registrationDate":"2022-10-19","registrationID":"https://pse.komdigi.go.id/tdpse-detail/11883","raw":{"id":"9cb1ac04-a807-4d4d-a398-b38fbf3a9e7b","nama_pse":"SAKA UNITI INDONESIA","nama_se":"GOKOMODO","sektor":"Sektor Teknologi Informasi dan Komunikasi","tanggal_terbit":"2022-10-19","url_tdpse_detail":"https://pse.komdigi.go.id/tdpse-detail/11883","website":"gokomodo.com"}},"3072":{"registrationStatus":"DOMESTIK-TERDAFTAR","systemName":"GOKOMODO E-PROCUREMENT","systemUrl":"gokomodo.com","operatorSector":"Sektor Teknologi Informasi dan Komunikasi, Sektor Teknologi Informasi dan Komunikasi","operatorName":"SAKA UNITI INDONESIA","registrationDate":"2022-01-19","registrationID":"https://pse.komdigi.go.id/tdpse-detail/3072","raw":{"id":"9cb1ab78-7e26-4bf4-978e-765aff044cff","nama_pse":"SAKA UNITI INDONESIA","nama_se":"GOKOMODO E-PROCUREMENT","sektor":"Sektor Teknologi Informasi dan Komunikasi, Sektor Teknologi Informasi dan Komunikasi","tanggal_terbit":"2022-01-19","url_tdpse_detail":"https://pse.komdigi.go.id/tdpse-detail/3072","website":"gokomodo.com"}},"3212":{"registrationStatus":"DOMESTIK-TERDAFTAR","systemName":"GOKOMODO E-COMMERCE","systemUrl":"gokomodo.com","operatorSector":"Sektor Teknologi Informasi dan Komunikasi, Sektor Teknologi Informasi dan Komunikasi","operatorName":"GOKOMODO UNITI INDONESIA","registrationDate":"2022-02-09","registrationID":"https://pse.komdigi.go.id/tdpse-detail/3212","raw":{"id":"9cb1ab90-b8c0-4fce-bfce-1635c567a329","nama_pse":"GOKOMODO UNITI INDONESIA","nama_se":"GOKOMODO E-COMMERCE","sektor":"Sektor Teknologi Informasi dan Komunikasi, Sektor Teknologi Informasi dan Komunikasi","tanggal_terbit":"2022-02-09","url_tdpse_detail":"https://pse.komdigi.go.id/tdpse-detail/3212","website":"gokomodo.com"}}}