{"8129":{"registrationStatus":"DOMESTIK-TERDAFTAR","systemName":"IN LEAF INDONESIA","systemUrl":"inleafindonesia.com","operatorSector":"Sektor Kesehatan","operatorName":"INTINUSA NATURAL MAXIMA","registrationDate":"2022-07-20","registrationID":"https://pse.komdigi.go.id/tdpse-detail/8129","raw":{"id":"9cb1abc7-d987-4f12-b755-60c9f686085c","nama_pse":"INTINUSA NATURAL MAXIMA","nama_se":"IN LEAF INDONESIA","sektor":"Sektor Kesehatan","tanggal_terbit":"2022-07-20","url_tdpse_detail":"https://pse.komdigi.go.id/tdpse-detail/8129","website":"inleafindonesia.com"}}}