{"15100":{"registrationStatus":"DOMESTIK-TERDAFTAR","systemName":"LA TIKET","systemUrl":"latiket.com","operatorSector":"Sektor Perdagangan, Sektor Teknologi Informasi dan Komunikasi","operatorName":"ORBIS ELITE INDUSTRIES","registrationDate":"2023-06-22","registrationID":"https://pse.komdigi.go.id/tdpse-detail/15100","raw":{"id":"9cb1ac24-0ba8-4079-a382-8afa1f86d0a8","nama_pse":"ORBIS ELITE INDUSTRIES","nama_se":"LA TIKET","sektor":"Sektor Perdagangan, Sektor Teknologi Informasi dan Komunikasi","tanggal_terbit":"2023-06-22","url_tdpse_detail":"https://pse.komdigi.go.id/tdpse-detail/15100","website":"latiket.com"}}}