{"19353":{"registrationStatus":"DOMESTIK-TERDAFTAR","systemName":"WWW.MEDIAPRODESA.COM","systemUrl":"mediaprodesa.com","operatorSector":"Sektor Teknologi Informasi dan Komunikasi","operatorName":"MEDIA PRO DESA","registrationDate":"2024-07-04","registrationID":"https://pse.komdigi.go.id/tdpse-detail/19353","raw":{"id":"9cb1ac5d-6ddb-4005-a1ef-57a903db5aa3","nama_pse":"MEDIA PRO DESA","nama_se":"WWW.MEDIAPRODESA.COM","sektor":"Sektor Teknologi Informasi dan Komunikasi","tanggal_terbit":"2024-07-04","url_tdpse_detail":"https://pse.komdigi.go.id/tdpse-detail/19353","website":"mediaprodesa.com"}}}