{"13445":{"registrationStatus":"DOMESTIK-TERDAFTAR","systemName":"MOBILSIA.COM","systemUrl":"mobilsia.com","operatorSector":"Sektor Teknologi Informasi dan Komunikasi","operatorName":"TAUFIK","registrationDate":"2023-01-06","registrationID":"https://pse.komdigi.go.id/tdpse-detail/13445","raw":{"id":"9cb1ac2b-9bb1-490b-8009-c7b616d22f4c","nama_pse":"TAUFIK","nama_se":"MOBILSIA.COM","sektor":"Sektor Teknologi Informasi dan Komunikasi","tanggal_terbit":"2023-01-06","url_tdpse_detail":"https://pse.komdigi.go.id/tdpse-detail/13445","website":"mobilsia.com"}}}