{"11787":{"registrationStatus":"DOMESTIK-TERDAFTAR","systemName":"MULAI WEB INDONESIA","systemUrl":"mulaiweb.com","operatorSector":"Sektor Teknologi Informasi dan Komunikasi","operatorName":"MULAI WEB INDONESIA","registrationDate":"2022-10-13","registrationID":"https://pse.komdigi.go.id/tdpse-detail/11787","raw":{"id":"9cb1ac04-01c3-46f1-9f63-d9c1653372d4","nama_pse":"MULAI WEB INDONESIA","nama_se":"MULAI WEB INDONESIA","sektor":"Sektor Teknologi Informasi dan Komunikasi","tanggal_terbit":"2022-10-13","url_tdpse_detail":"https://pse.komdigi.go.id/tdpse-detail/11787","website":"mulaiweb.com"}}}