{"9911":{"registrationStatus":"ASING-TERDAFTAR","systemName":"NUADU","systemUrl":"nuadu.com","operatorSector":"Sektor Teknologi Informasi dan Komunikasi","operatorName":"NUADU","registrationDate":"2022-08-04","registrationID":"https://pse.komdigi.go.id/tdpse-detail/9911","raw":{"id":"9cb1abd4-60a4-4282-a840-45f6acc6c68c","nama_pse":"NUADU","nama_se":"NUADU","sektor":"Sektor Teknologi Informasi dan Komunikasi","tanggal_terbit":"2022-08-04","url_tdpse_detail":"https://pse.komdigi.go.id/tdpse-detail/9911","website":"nuadu.com"}}}