{"17240":{"registrationStatus":"DOMESTIK-TERDAFTAR","systemName":"SIMDEA","systemUrl":"rsetty-batu.com","operatorSector":"Sektor Kesehatan","operatorName":"TRIDEA UTAMA","registrationDate":"2024-01-06","registrationID":"https://pse.komdigi.go.id/tdpse-detail/17240","raw":{"id":"9cb1ac66-7639-40b0-a314-3fa1dc180785","nama_pse":"TRIDEA UTAMA","nama_se":"SIMDEA","sektor":"Sektor Kesehatan","tanggal_terbit":"2024-01-06","url_tdpse_detail":"https://pse.komdigi.go.id/tdpse-detail/17240","website":"rsetty-batu.com"}}}