{"4492":{"registrationStatus":"DOMESTIK-TERDAFTAR","systemName":"RUNCHISE","systemUrl":"runchise.com","operatorSector":"Sektor Teknologi Informasi dan Komunikasi","operatorName":"TEKNOLOGI KULINER KEKINIAN","registrationDate":"2022-05-18","registrationID":"https://pse.komdigi.go.id/tdpse-detail/4492","raw":{"id":"9cb1aba3-3291-4396-86fa-276bac5d29a8","nama_pse":"TEKNOLOGI KULINER KEKINIAN","nama_se":"RUNCHISE","sektor":"Sektor Teknologi Informasi dan Komunikasi","tanggal_terbit":"2022-05-18","url_tdpse_detail":"https://pse.komdigi.go.id/tdpse-detail/4492","website":"runchise.com"}}}