{"3261":{"registrationStatus":"DOMESTIK-TERDAFTAR","systemName":"TEMPATJUALAN","systemUrl":"tempatjualan.com","operatorSector":"Sektor Perdagangan, Sektor Perdagangan, Sektor Teknologi Informasi dan Komunikasi, Sektor Teknologi Informasi dan Komunikasi","operatorName":"ZONA MAKMUR","registrationDate":"2022-02-16","registrationID":"https://pse.komdigi.go.id/tdpse-detail/3261","raw":{"id":"9cb1ab8a-c1f5-4746-a692-590bc6541c54","nama_pse":"ZONA MAKMUR","nama_se":"TEMPATJUALAN","sektor":"Sektor Perdagangan, Sektor Perdagangan, Sektor Teknologi Informasi dan Komunikasi, Sektor Teknologi Informasi dan Komunikasi","tanggal_terbit":"2022-02-16","url_tdpse_detail":"https://pse.komdigi.go.id/tdpse-detail/3261","website":"tempatjualan.com"}}}