{"14661":{"registrationStatus":"ASING-DIHENTIKAN-SEMENTARA","systemName":"OWENSTRATEGIKMEDIA","systemUrl":"tigerbitumen.com","operatorSector":"Sektor Keuangan","operatorName":"SHANTOU JINJIA TRADING CO., LTD.","registrationDate":"2023-05-14","registrationID":"https://pse.komdigi.go.id/tdpse-detail/14661","raw":{"id":"9cb1ac43-922d-49c3-80a5-a9ea848b6f33","nama_pse":"SHANTOU JINJIA TRADING CO., LTD.","nama_se":"OWENSTRATEGIKMEDIA","sektor":"Sektor Keuangan","tanggal_terbit":"2023-05-14","url_tdpse_detail":"https://pse.komdigi.go.id/tdpse-detail/14661","website":"tigerbitumen.com"}},"14682":{"registrationStatus":"ASING-DIHENTIKAN-SEMENTARA","systemName":"SEKOLAH OLAHRAGA PEMBANGUNAN JAYA","systemUrl":"tigerbitumen.com","operatorSector":"Sektor Keuangan","operatorName":"SEKOLAH TUNAS INDONESIA","registrationDate":"2023-05-14","registrationID":"https://pse.komdigi.go.id/tdpse-detail/14682","raw":{"id":"9cb1ac43-a86b-48a0-94e5-63c0443c7bd2","nama_pse":"SEKOLAH TUNAS INDONESIA","nama_se":"SEKOLAH OLAHRAGA PEMBANGUNAN JAYA","sektor":"Sektor Keuangan","tanggal_terbit":"2023-05-14","url_tdpse_detail":"https://pse.komdigi.go.id/tdpse-detail/14682","website":"tigerbitumen.com"}},"14685":{"registrationStatus":"ASING-DIHENTIKAN-SEMENTARA","systemName":"PEMBANGUNAN JAYA","systemUrl":"tigerbitumen.com","operatorSector":"Sektor Keuangan","operatorName":"SHANTOU MARIA INVESTMENT CO., LTD.","registrationDate":"2023-05-14","registrationID":"https://pse.komdigi.go.id/tdpse-detail/14685","raw":{"id":"9cb1ac21-c4b4-43f7-a089-30341e2754c4","nama_pse":"SHANTOU MARIA INVESTMENT CO., LTD.","nama_se":"PEMBANGUNAN JAYA","sektor":"Sektor Keuangan","tanggal_terbit":"2023-05-14","url_tdpse_detail":"https://pse.komdigi.go.id/tdpse-detail/14685","website":"tigerbitumen.com"}}}