{"6774":{"registrationStatus":"DOMESTIK-TERDAFTAR","systemName":"UBIKLAN.COM","systemUrl":"ubiklan.com","operatorSector":"Sektor Teknologi Informasi dan Komunikasi","operatorName":"HELPIO GLOVIN TEKNOLOGI","registrationDate":"2022-07-19","registrationID":"https://pse.komdigi.go.id/tdpse-detail/6774","raw":{"id":"9cb1abb5-b7d1-4353-a8ad-06b9bf59f4b1","nama_pse":"HELPIO GLOVIN TEKNOLOGI","nama_se":"UBIKLAN.COM","sektor":"Sektor Teknologi Informasi dan Komunikasi","tanggal_terbit":"2022-07-19","url_tdpse_detail":"https://pse.komdigi.go.id/tdpse-detail/6774","website":"ubiklan.com"}}}