{"13438":{"registrationStatus":"DOMESTIK-TERDAFTAR","systemName":"BIMASOFT","systemUrl":"bimasoft.web.id","operatorSector":"Sektor Perdagangan","operatorName":"BIMASOFT","registrationDate":"2023-01-06","registrationID":"https://pse.komdigi.go.id/tdpse-detail/13438","raw":{"id":"9cb1ac2b-7584-4369-96af-59918fdf2367","nama_pse":"BIMASOFT","nama_se":"BIMASOFT","sektor":"Sektor Perdagangan","tanggal_terbit":"2023-01-06","url_tdpse_detail":"https://pse.komdigi.go.id/tdpse-detail/13438","website":"bimasoft.web.id"}}}