{"6354":{"registrationStatus":"DOMESTIK-TERDAFTAR","systemName":"DASHBOARD LENDER","systemUrl":"danaku.danakini.co.id","operatorSector":"Sektor Keuangan","operatorName":"DANA KINI INDONESIA","registrationDate":"2022-07-18","registrationID":"https://pse.komdigi.go.id/tdpse-detail/6354","raw":{"id":"9cb1abb4-5cef-462d-a3ec-99575ffdf435","nama_pse":"DANA KINI INDONESIA","nama_se":"DASHBOARD LENDER","sektor":"Sektor Keuangan","tanggal_terbit":"2022-07-18","url_tdpse_detail":"https://pse.komdigi.go.id/tdpse-detail/6354","website":"danaku.danakini.co.id"}}}