{"875":{"registrationStatus":"DOMESTIK-TERDAFTAR","systemName":"ONBOARDING WEBSITE","systemUrl":"onestore.ocbcnisp.com","operatorSector":"Sektor Keuangan, Sektor Keuangan, Sektor Keuangan","operatorName":"BANK OCBC NISP","registrationDate":"2021-05-11","registrationID":"https://pse.komdigi.go.id/tdpse-detail/875","raw":{"id":"9cb1abaa-e1d5-4e76-9450-04ea4737f83b","nama_pse":"BANK OCBC NISP","nama_se":"ONBOARDING WEBSITE","sektor":"Sektor Keuangan, Sektor Keuangan, Sektor Keuangan","tanggal_terbit":"2021-05-11","url_tdpse_detail":"https://pse.komdigi.go.id/tdpse-detail/875","website":"onestore.ocbcnisp.com"}}}