{"21820":{"registrationStatus":"DOMESTIK-TERDAFTAR","systemName":"SOFTWARE AS A SERVICES (SAAS) BERBASIS BLOCKCHAIN UNTUK DIGITAL PHILANTHROPY (PBX)","systemUrl":"pbxgive.co","operatorSector":"Sektor Teknologi Informasi dan Komunikasi","operatorName":"IBANTU SOLUSI SYARIAH","registrationDate":"2024-12-17","registrationID":"https://pse.komdigi.go.id/tdpse-detail/21820","raw":{"id":"9dbebaaf-f4de-4d75-b09c-0f6b2031f7a1","nama_pse":"IBANTU SOLUSI SYARIAH","nama_se":"SOFTWARE AS A SERVICES (SAAS) BERBASIS BLOCKCHAIN UNTUK DIGITAL PHILANTHROPY (PBX)","sektor":"Sektor Teknologi Informasi dan Komunikasi","tanggal_terbit":"2024-12-17","url_tdpse_detail":"https://pse.komdigi.go.id/tdpse-detail/21820","website":"pbxgive.co"}}}